crest/__init__.py
crest/api.py
crest/app.py
crest/cli.py
crest/pages.py
crest/server.py
crest/templates.py
crestwebframework-1.0.4.dist-info/METADATA
crestwebframework-1.0.4.dist-info/WHEEL
crestwebframework-1.0.4.dist-info/top_level.txt
crestwebframework-1.0.4.dist-info/RECORD
