Metadata-Version: 2.1
Name: crestwebframework
Version: 1.0.4
Summary: A web framework designed for simplicity and efficiency
Author: William Herring
Author-email: William Herring <william.herring.au@gmail.com>
Project-URL: Homepage, https://william-herring.github.io/crest
Project-URL: Repository, https://github.com/william-herring/crest
Keywords: web,framework,crest
Classifier: License :: OSI Approved :: MIT License
Classifier: Programming Language :: Python
Classifier: Programming Language :: Python :: 3
Requires-Python: >=3.7
Requires-Dist: typer (>=0.7.0)
Requires-Dist: rich (>=12.6.0)
Provides-Extra: dev
Requires-Dist: pytest ; extra == 'dev'
